{
   "runs" : [
      {
         "OS" : "linux",
         "abstract" : "Call many Geo-Coders",
         "dir" : "/home/runner/work/Geo-Coder-List/Geo-Coder-List",
         "finish" : 1780452387.22605,
         "name" : "Geo-Coder-List",
         "perl" : "5.40.4",
         "run" : "-e",
         "start" : 1780452387.22563,
         "version" : "0.36"
      },
      {
         "OS" : "linux",
         "abstract" : "Call many Geo-Coders",
         "dir" : "/home/runner/work/Geo-Coder-List/Geo-Coder-List",
         "finish" : 1780452387.40161,
         "name" : "Geo-Coder-List",
         "perl" : "5.40.4",
         "run" : "-e",
         "start" : 1780452387.40135,
         "version" : "0.36"
      },
      {
         "OS" : "linux",
         "abstract" : "Call many Geo-Coders",
         "dir" : "/home/runner/work/Geo-Coder-List/Geo-Coder-List",
         "finish" : 1780452387.56838,
         "name" : "Geo-Coder-List",
         "perl" : "5.40.4",
         "run" : "-e",
         "start" : 1780452387.56799,
         "version" : "0.36"
      },
      {
         "OS" : "linux",
         "abstract" : "Call many Geo-Coders",
         "dir" : "/home/runner/work/Geo-Coder-List/Geo-Coder-List",
         "finish" : 1780452387.73718,
         "name" : "Geo-Coder-List",
         "perl" : "5.40.4",
         "run" : "-e",
         "start" : 1780452387.73678,
         "version" : "0.36"
      },
      {
         "OS" : "linux",
         "abstract" : "Call many Geo-Coders",
         "dir" : "/home/runner/work/Geo-Coder-List/Geo-Coder-List",
         "finish" : 1780452387.9086,
         "name" : "Geo-Coder-List",
         "perl" : "5.40.4",
         "run" : "-e",
         "start" : 1780452387.90832,
         "version" : "0.36"
      },
      {
         "OS" : "linux",
         "abstract" : "Call many Geo-Coders",
         "dir" : "/home/runner/work/Geo-Coder-List/Geo-Coder-List",
         "finish" : 1780452388.07488,
         "name" : "Geo-Coder-List",
         "perl" : "5.40.4",
         "run" : "-e",
         "start" : 1780452388.07464,
         "version" : "0.36"
      },
      {
         "OS" : "linux",
         "abstract" : "Call many Geo-Coders",
         "dir" : "/home/runner/work/Geo-Coder-List/Geo-Coder-List",
         "finish" : 1780452388.23958,
         "name" : "Geo-Coder-List",
         "perl" : "5.40.4",
         "run" : "-e",
         "start" : 1780452388.23927,
         "version" : "0.36"
      },
      {
         "OS" : "linux",
         "abstract" : "Call many Geo-Coders",
         "dir" : "/home/runner/work/Geo-Coder-List/Geo-Coder-List",
         "finish" : 1780452388.40349,
         "name" : "Geo-Coder-List",
         "perl" : "5.40.4",
         "run" : "-e",
         "start" : 1780452388.40313,
         "version" : "0.36"
      },
      {
         "OS" : "linux",
         "abstract" : "Call many Geo-Coders",
         "dir" : "/home/runner/work/Geo-Coder-List/Geo-Coder-List",
         "finish" : 1780452388.59881,
         "name" : "Geo-Coder-List",
         "perl" : "5.40.4",
         "run" : "-e",
         "start" : 1780452388.58895,
         "version" : "0.36"
      },
      {
         "OS" : "linux",
         "abstract" : "Call many Geo-Coders",
         "dir" : "/home/runner/work/Geo-Coder-List/Geo-Coder-List",
         "finish" : 1780452405.38565,
         "name" : "Geo-Coder-List",
         "perl" : "5.40.4",
         "run" : "-e",
         "start" : 1780452388.79775,
         "version" : "0.36"
      },
      {
         "OS" : "linux",
         "abstract" : "Call many Geo-Coders",
         "dir" : "/home/runner/work/Geo-Coder-List/Geo-Coder-List",
         "finish" : 1780452388.95556,
         "name" : "Geo-Coder-List",
         "perl" : "5.40.4",
         "run" : "-e",
         "start" : 1780452388.95545,
         "version" : "0.36"
      },
      {
         "OS" : "linux",
         "abstract" : "Call many Geo-Coders",
         "dir" : "/home/runner/work/Geo-Coder-List/Geo-Coder-List",
         "finish" : 1780452389.26514,
         "name" : "Geo-Coder-List",
         "perl" : "5.40.4",
         "run" : "t/00-load.t",
         "start" : 1780452389.2639,
         "version" : "0.36"
      },
      {
         "OS" : "linux",
         "abstract" : "Call many Geo-Coders",
         "dir" : "/home/runner/work/Geo-Coder-List/Geo-Coder-List",
         "finish" : 1780452389.736,
         "name" : "Geo-Coder-List",
         "perl" : "5.40.4",
         "run" : "t/10-new.t",
         "start" : 1780452389.69954,
         "version" : "0.36"
      },
      {
         "OS" : "linux",
         "abstract" : "Call many Geo-Coders",
         "dir" : "/home/runner/work/Geo-Coder-List/Geo-Coder-List",
         "finish" : 1780452390.24718,
         "name" : "Geo-Coder-List",
         "perl" : "5.40.4",
         "run" : "t/30-basics.t",
         "start" : 1780452390.20171,
         "version" : "0.36"
      },
      {
         "OS" : "linux",
         "abstract" : "Call many Geo-Coders",
         "dir" : "/home/runner/work/Geo-Coder-List/Geo-Coder-List",
         "finish" : 1780452390.72161,
         "name" : "Geo-Coder-List",
         "perl" : "5.40.4",
         "run" : "t/bing.t",
         "start" : 1780452390.70198,
         "version" : "0.36"
      },
      {
         "OS" : "linux",
         "abstract" : "Call many Geo-Coders",
         "dir" : "/home/runner/work/Geo-Coder-List/Geo-Coder-List",
         "finish" : 1780452391.11186,
         "name" : "Geo-Coder-List",
         "perl" : "5.40.4",
         "run" : "t/boiler.t",
         "start" : 1780452391.0935,
         "version" : "0.36"
      },
      {
         "OS" : "linux",
         "abstract" : "Call many Geo-Coders",
         "dir" : "/home/runner/work/Geo-Coder-List/Geo-Coder-List",
         "finish" : 1780452391.38176,
         "name" : "Geo-Coder-List",
         "perl" : "5.40.4",
         "run" : "t/cache.t",
         "start" : 1780452391.3815,
         "version" : "0.36"
      },
      {
         "OS" : "linux",
         "abstract" : "Call many Geo-Coders",
         "dir" : "/home/runner/work/Geo-Coder-List/Geo-Coder-List",
         "finish" : 1780452391.73576,
         "name" : "Geo-Coder-List",
         "perl" : "5.40.4",
         "run" : "t/canada.t",
         "start" : 1780452391.71727,
         "version" : "0.36"
      },
      {
         "OS" : "linux",
         "abstract" : "Call many Geo-Coders",
         "dir" : "/home/runner/work/Geo-Coder-List/Geo-Coder-List",
         "finish" : 1780452392.17753,
         "name" : "Geo-Coder-List",
         "perl" : "5.40.4",
         "run" : "t/carp.t",
         "start" : 1780452392.17716,
         "version" : "0.36"
      },
      {
         "OS" : "linux",
         "abstract" : "Call many Geo-Coders",
         "dir" : "/home/runner/work/Geo-Coder-List/Geo-Coder-List",
         "finish" : 1780452392.62805,
         "name" : "Geo-Coder-List",
         "perl" : "5.40.4",
         "run" : "t/census.t",
         "start" : 1780452392.61091,
         "version" : "0.36"
      },
      {
         "OS" : "linux",
         "abstract" : "Call many Geo-Coders",
         "dir" : "/home/runner/work/Geo-Coder-List/Geo-Coder-List",
         "finish" : 1780452393.00013,
         "name" : "Geo-Coder-List",
         "perl" : "5.40.4",
         "run" : "t/changes.t",
         "start" : 1780452392.99984,
         "version" : "0.36"
      },
      {
         "OS" : "linux",
         "abstract" : "Call many Geo-Coders",
         "dir" : "/home/runner/work/Geo-Coder-List/Geo-Coder-List",
         "finish" : 1780452393.23694,
         "name" : "Geo-Coder-List",
         "perl" : "5.40.4",
         "run" : "t/comment-spelling.t",
         "start" : 1780452393.23664,
         "version" : "0.36"
      },
      {
         "OS" : "linux",
         "abstract" : "Call many Geo-Coders",
         "dir" : "/home/runner/work/Geo-Coder-List/Geo-Coder-List",
         "finish" : 1780452393.47401,
         "name" : "Geo-Coder-List",
         "perl" : "5.40.4",
         "run" : "t/critic.t",
         "start" : 1780452393.47372,
         "version" : "0.36"
      },
      {
         "OS" : "linux",
         "abstract" : "Call many Geo-Coders",
         "dir" : "/home/runner/work/Geo-Coder-List/Geo-Coder-List",
         "finish" : 1780452393.71361,
         "name" : "Geo-Coder-List",
         "perl" : "5.40.4",
         "run" : "t/cv.t",
         "start" : 1780452393.71332,
         "version" : "0.36"
      },
      {
         "OS" : "linux",
         "abstract" : "Call many Geo-Coders",
         "dir" : "/home/runner/work/Geo-Coder-List/Geo-Coder-List",
         "finish" : 1780452393.94919,
         "name" : "Geo-Coder-List",
         "perl" : "5.40.4",
         "run" : "t/dist.t",
         "start" : 1780452393.94889,
         "version" : "0.36"
      },
      {
         "OS" : "linux",
         "abstract" : "Call many Geo-Coders",
         "dir" : "/home/runner/work/Geo-Coder-List/Geo-Coder-List",
         "finish" : 1780452394.18474,
         "name" : "Geo-Coder-List",
         "perl" : "5.40.4",
         "run" : "t/eof.t",
         "start" : 1780452394.18446,
         "version" : "0.36"
      },
      {
         "OS" : "linux",
         "abstract" : "Call many Geo-Coders",
         "dir" : "/home/runner/work/Geo-Coder-List/Geo-Coder-List",
         "finish" : 1780452394.42226,
         "name" : "Geo-Coder-List",
         "perl" : "5.40.4",
         "run" : "t/eol.t",
         "start" : 1780452394.42196,
         "version" : "0.36"
      },
      {
         "OS" : "linux",
         "abstract" : "Call many Geo-Coders",
         "dir" : "/home/runner/work/Geo-Coder-List/Geo-Coder-List",
         "finish" : 1780452394.76997,
         "name" : "Geo-Coder-List",
         "perl" : "5.40.4",
         "run" : "t/free.t",
         "start" : 1780452394.75308,
         "version" : "0.36"
      },
      {
         "OS" : "linux",
         "abstract" : "Call many Geo-Coders",
         "dir" : "/home/runner/work/Geo-Coder-List/Geo-Coder-List",
         "finish" : 1780452395.08776,
         "name" : "Geo-Coder-List",
         "perl" : "5.40.4",
         "run" : "t/fuzz.t",
         "start" : 1780452395.08772,
         "version" : "0.36"
      },
      {
         "OS" : "linux",
         "abstract" : "Call many Geo-Coders",
         "dir" : "/home/runner/work/Geo-Coder-List/Geo-Coder-List",
         "finish" : 1780452395.32422,
         "name" : "Geo-Coder-List",
         "perl" : "5.40.4",
         "run" : "t/geoapify.t",
         "start" : 1780452395.32393,
         "version" : "0.36"
      },
      {
         "OS" : "linux",
         "abstract" : "Call many Geo-Coders",
         "dir" : "/home/runner/work/Geo-Coder-List/Geo-Coder-List",
         "finish" : 1780452395.66037,
         "name" : "Geo-Coder-List",
         "perl" : "5.40.4",
         "run" : "t/geofarm.t",
         "start" : 1780452395.64083,
         "version" : "0.36"
      },
      {
         "OS" : "linux",
         "abstract" : "Call many Geo-Coders",
         "dir" : "/home/runner/work/Geo-Coder-List/Geo-Coder-List",
         "finish" : 1780452396.12281,
         "name" : "Geo-Coder-List",
         "perl" : "5.40.4",
         "run" : "t/geonames.t",
         "start" : 1780452396.10409,
         "version" : "0.36"
      },
      {
         "OS" : "linux",
         "abstract" : "Call many Geo-Coders",
         "dir" : "/home/runner/work/Geo-Coder-List/Geo-Coder-List",
         "finish" : 1780452396.58449,
         "name" : "Geo-Coder-List",
         "perl" : "5.40.4",
         "run" : "t/google.t",
         "start" : 1780452396.5654,
         "version" : "0.36"
      },
      {
         "OS" : "linux",
         "abstract" : "Call many Geo-Coders",
         "dir" : "/home/runner/work/Geo-Coder-List/Geo-Coder-List",
         "finish" : 1780452397.04715,
         "name" : "Geo-Coder-List",
         "perl" : "5.40.4",
         "run" : "t/googleplaces.t",
         "start" : 1780452397.02882,
         "version" : "0.36"
      },
      {
         "OS" : "linux",
         "abstract" : "Call many Geo-Coders",
         "dir" : "/home/runner/work/Geo-Coder-List/Geo-Coder-List",
         "finish" : 1780452397.41482,
         "name" : "Geo-Coder-List",
         "perl" : "5.40.4",
         "run" : "t/gv.t",
         "start" : 1780452397.41452,
         "version" : "0.36"
      },
      {
         "OS" : "linux",
         "abstract" : "Call many Geo-Coders",
         "dir" : "/home/runner/work/Geo-Coder-List/Geo-Coder-List",
         "finish" : 1780452397.64807,
         "name" : "Geo-Coder-List",
         "perl" : "5.40.4",
         "run" : "t/kwalitee.t",
         "start" : 1780452397.64778,
         "version" : "0.36"
      },
      {
         "OS" : "linux",
         "abstract" : "Call many Geo-Coders",
         "dir" : "/home/runner/work/Geo-Coder-List/Geo-Coder-List",
         "finish" : 1780452397.98813,
         "name" : "Geo-Coder-List",
         "perl" : "5.40.4",
         "run" : "t/list.t",
         "start" : 1780452397.95877,
         "version" : "0.36"
      },
      {
         "OS" : "linux",
         "abstract" : "Call many Geo-Coders",
         "dir" : "/home/runner/work/Geo-Coder-List/Geo-Coder-List",
         "finish" : 1780452398.37441,
         "name" : "Geo-Coder-List",
         "perl" : "5.40.4",
         "run" : "t/manifest.t",
         "start" : 1780452398.37412,
         "version" : "0.36"
      },
      {
         "OS" : "linux",
         "abstract" : "Call many Geo-Coders",
         "dir" : "/home/runner/work/Geo-Coder-List/Geo-Coder-List",
         "finish" : 1780452398.71118,
         "name" : "Geo-Coder-List",
         "perl" : "5.40.4",
         "run" : "t/mapbox.t",
         "start" : 1780452398.69138,
         "version" : "0.36"
      },
      {
         "OS" : "linux",
         "abstract" : "Call many Geo-Coders",
         "dir" : "/home/runner/work/Geo-Coder-List/Geo-Coder-List",
         "finish" : 1780452399.11255,
         "name" : "Geo-Coder-List",
         "perl" : "5.40.4",
         "run" : "t/mock.t",
         "start" : 1780452399.11223,
         "version" : "0.36"
      },
      {
         "OS" : "linux",
         "abstract" : "Call many Geo-Coders",
         "dir" : "/home/runner/work/Geo-Coder-List/Geo-Coder-List",
         "finish" : 1780452399.35284,
         "name" : "Geo-Coder-List",
         "perl" : "5.40.4",
         "run" : "t/no404s.t",
         "start" : 1780452399.35257,
         "version" : "0.36"
      },
      {
         "OS" : "linux",
         "abstract" : "Call many Geo-Coders",
         "dir" : "/home/runner/work/Geo-Coder-List/Geo-Coder-List",
         "finish" : 1780452399.589,
         "name" : "Geo-Coder-List",
         "perl" : "5.40.4",
         "run" : "t/noplan.t",
         "start" : 1780452399.5887,
         "version" : "0.36"
      },
      {
         "OS" : "linux",
         "abstract" : "Call many Geo-Coders",
         "dir" : "/home/runner/work/Geo-Coder-List/Geo-Coder-List",
         "finish" : 1780452399.9251,
         "name" : "Geo-Coder-List",
         "perl" : "5.40.4",
         "run" : "t/opencage.t",
         "start" : 1780452399.90672,
         "version" : "0.36"
      },
      {
         "OS" : "linux",
         "abstract" : "Call many Geo-Coders",
         "dir" : "/home/runner/work/Geo-Coder-List/Geo-Coder-List",
         "finish" : 1780452400.40052,
         "name" : "Geo-Coder-List",
         "perl" : "5.40.4",
         "run" : "t/osm.t",
         "start" : 1780452400.37762,
         "version" : "0.36"
      },
      {
         "OS" : "linux",
         "abstract" : "Call many Geo-Coders",
         "dir" : "/home/runner/work/Geo-Coder-List/Geo-Coder-List",
         "finish" : 1780452400.87496,
         "name" : "Geo-Coder-List",
         "perl" : "5.40.4",
         "run" : "t/ovi.t",
         "start" : 1780452400.85526,
         "version" : "0.36"
      },
      {
         "OS" : "linux",
         "abstract" : "Call many Geo-Coders",
         "dir" : "/home/runner/work/Geo-Coder-List/Geo-Coder-List",
         "finish" : 1780452401.26775,
         "name" : "Geo-Coder-List",
         "perl" : "5.40.4",
         "run" : "t/pod-cm.t",
         "start" : 1780452401.2668,
         "version" : "0.36"
      },
      {
         "OS" : "linux",
         "abstract" : "Call many Geo-Coders",
         "dir" : "/home/runner/work/Geo-Coder-List/Geo-Coder-List",
         "finish" : 1780452401.50869,
         "name" : "Geo-Coder-List",
         "perl" : "5.40.4",
         "run" : "t/pod-coverage.t",
         "start" : 1780452401.50842,
         "version" : "0.36"
      },
      {
         "OS" : "linux",
         "abstract" : "Call many Geo-Coders",
         "dir" : "/home/runner/work/Geo-Coder-List/Geo-Coder-List",
         "finish" : 1780452401.74355,
         "name" : "Geo-Coder-List",
         "perl" : "5.40.4",
         "run" : "t/pod-links.t",
         "start" : 1780452401.74326,
         "version" : "0.36"
      },
      {
         "OS" : "linux",
         "abstract" : "Call many Geo-Coders",
         "dir" : "/home/runner/work/Geo-Coder-List/Geo-Coder-List",
         "finish" : 1780452401.97616,
         "name" : "Geo-Coder-List",
         "perl" : "5.40.4",
         "run" : "t/pod-snippets.t",
         "start" : 1780452401.97589,
         "version" : "0.36"
      },
      {
         "OS" : "linux",
         "abstract" : "Call many Geo-Coders",
         "dir" : "/home/runner/work/Geo-Coder-List/Geo-Coder-List",
         "finish" : 1780452402.20574,
         "name" : "Geo-Coder-List",
         "perl" : "5.40.4",
         "run" : "t/pod-spelling.t",
         "start" : 1780452402.20551,
         "version" : "0.36"
      },
      {
         "OS" : "linux",
         "abstract" : "Call many Geo-Coders",
         "dir" : "/home/runner/work/Geo-Coder-List/Geo-Coder-List",
         "finish" : 1780452402.44062,
         "name" : "Geo-Coder-List",
         "perl" : "5.40.4",
         "run" : "t/pod-synopsis.t",
         "start" : 1780452402.44034,
         "version" : "0.36"
      },
      {
         "OS" : "linux",
         "abstract" : "Call many Geo-Coders",
         "dir" : "/home/runner/work/Geo-Coder-List/Geo-Coder-List",
         "finish" : 1780452402.66999,
         "name" : "Geo-Coder-List",
         "perl" : "5.40.4",
         "run" : "t/pod.t",
         "start" : 1780452402.66973,
         "version" : "0.36"
      },
      {
         "OS" : "linux",
         "abstract" : "Call many Geo-Coders",
         "dir" : "/home/runner/work/Geo-Coder-List/Geo-Coder-List",
         "finish" : 1780452403.00967,
         "name" : "Geo-Coder-List",
         "perl" : "5.40.4",
         "run" : "t/postcodes.t",
         "start" : 1780452402.98547,
         "version" : "0.36"
      },
      {
         "OS" : "linux",
         "abstract" : "Call many Geo-Coders",
         "dir" : "/home/runner/work/Geo-Coder-List/Geo-Coder-List",
         "finish" : 1780452403.40006,
         "name" : "Geo-Coder-List",
         "perl" : "5.40.4",
         "run" : "t/rand.t",
         "start" : 1780452403.39977,
         "version" : "0.36"
      },
      {
         "OS" : "linux",
         "abstract" : "Call many Geo-Coders",
         "dir" : "/home/runner/work/Geo-Coder-List/Geo-Coder-List",
         "finish" : 1780452403.6858,
         "name" : "Geo-Coder-List",
         "perl" : "5.40.4",
         "run" : "t/ua.t",
         "start" : 1780452403.68526,
         "version" : "0.36"
      },
      {
         "OS" : "linux",
         "abstract" : "Call many Geo-Coders",
         "dir" : "/home/runner/work/Geo-Coder-List/Geo-Coder-List",
         "finish" : 1780452403.93216,
         "name" : "Geo-Coder-List",
         "perl" : "5.40.4",
         "run" : "t/unused.t",
         "start" : 1780452403.93187,
         "version" : "0.36"
      },
      {
         "OS" : "linux",
         "abstract" : "Call many Geo-Coders",
         "dir" : "/home/runner/work/Geo-Coder-List/Geo-Coder-List",
         "finish" : 1780452404.26318,
         "name" : "Geo-Coder-List",
         "perl" : "5.40.4",
         "run" : "t/us.t",
         "start" : 1780452404.24484,
         "version" : "0.36"
      },
      {
         "OS" : "linux",
         "abstract" : "Call many Geo-Coders",
         "dir" : "/home/runner/work/Geo-Coder-List/Geo-Coder-List",
         "finish" : 1780452404.63223,
         "name" : "Geo-Coder-List",
         "perl" : "5.40.4",
         "run" : "t/used.t",
         "start" : 1780452404.63195,
         "version" : "0.36"
      },
      {
         "OS" : "linux",
         "abstract" : "Call many Geo-Coders",
         "dir" : "/home/runner/work/Geo-Coder-List/Geo-Coder-List",
         "finish" : 1780452404.87035,
         "name" : "Geo-Coder-List",
         "perl" : "5.40.4",
         "run" : "t/vars.t",
         "start" : 1780452404.87,
         "version" : "0.36"
      },
      {
         "OS" : "linux",
         "abstract" : "Call many Geo-Coders",
         "dir" : "/home/runner/work/Geo-Coder-List/Geo-Coder-List",
         "finish" : 1780452405.20742,
         "name" : "Geo-Coder-List",
         "perl" : "5.40.4",
         "run" : "t/xyz.t",
         "start" : 1780452405.18804,
         "version" : "0.36"
      }
   ],
   "summary" : {
      "Total" : {
         "branch" : {
            "covered" : 66,
            "error" : 216,
            "percentage" : 23.4042553191489,
            "total" : 282,
            "uncoverable" : 0
         },
         "condition" : {
            "covered" : 33,
            "error" : 59,
            "percentage" : 35.8695652173913,
            "total" : 92,
            "uncoverable" : 0
         },
         "statement" : {
            "covered" : 170,
            "error" : 231,
            "percentage" : 42.3940149625935,
            "total" : 401
         },
         "subroutine" : {
            "covered" : 15,
            "error" : 3,
            "percentage" : 83.3333333333333,
            "total" : 18
         },
         "total" : {
            "covered" : 284,
            "error" : 509,
            "percentage" : 35.8133669609079,
            "total" : 793,
            "uncoverable" : 0
         }
      },
      "blib/lib/Geo/Coder/List.pm" : {
         "branch" : {
            "covered" : 66,
            "error" : 216,
            "percentage" : 23.4042553191489,
            "total" : 282,
            "uncoverable" : 0
         },
         "condition" : {
            "covered" : 33,
            "error" : 59,
            "percentage" : 35.8695652173913,
            "total" : 92,
            "uncoverable" : 0
         },
         "statement" : {
            "covered" : 170,
            "error" : 231,
            "percentage" : 42.3940149625935,
            "total" : 401
         },
         "subroutine" : {
            "covered" : 15,
            "error" : 3,
            "percentage" : 83.3333333333333,
            "total" : 18
         },
         "total" : {
            "covered" : 284,
            "error" : 509,
            "percentage" : 35.8133669609079,
            "total" : 793,
            "uncoverable" : 0
         }
      }
   }
}
